iris_dollar_list/__init__.py
iris_dollar_list/dollar_list.py
iris_dollar_list-0.9.6.dist-info/LICENSE
iris_dollar_list-0.9.6.dist-info/METADATA
iris_dollar_list-0.9.6.dist-info/WHEEL
iris_dollar_list-0.9.6.dist-info/top_level.txt
iris_dollar_list-0.9.6.dist-info/RECORD
