Metadata-Version: 2.1
Name: iris-dollar-list
Version: 0.9.6
Summary: iris-dollar-list
Home-page: https://github.com/grongierisc/iris-dollar-list
Author: grongier
Author-email: guillaume.rongier@intersystems.com
License: MIT
Keywords: iris-dollar-list
Classifier: Development Status :: 5 - Production/Stable
Classifier: Intended Audience :: Developers
Classifier: License :: OSI Approved :: MIT License
Classifier: Operating System :: OS Independent
Classifier: Programming Language :: Python :: 3.7
Classifier: Programming Language :: Python :: 3.8
Classifier: Programming Language :: Python :: 3.9
Classifier: Programming Language :: Python :: 3.10
Classifier: Programming Language :: Python :: 3.11
Classifier: Topic :: Utilities
License-File: LICENSE
